responsysrest/__init__.py
responsysrest/client.py
responsysrest/configuration.py
responsysrest/containers.py
responsysrest/credentials.py
responsysrest/objects.py
responsysrest-0.1.12.dist-info/LICENSE
responsysrest-0.1.12.dist-info/METADATA
responsysrest-0.1.12.dist-info/WHEEL
responsysrest-0.1.12.dist-info/top_level.txt
responsysrest-0.1.12.dist-info/RECORD
